{"Meta Data":{"1. Information":"Daily Prices (open, high, low, close) and Volumes","2. Symbol":"NAACU","3. Last Refreshed":"2021-02-11","4. Output Size":"Full size","5. Time Zone":"US/Eastern"},"Time Series (Daily)":{"2021-02-11":{"1. open":"10.6000","2. high":"10.6000","3. low":"10.5200","4. close":"10.5400","5. volume":"9639"},"2021-02-10":{"1. open":"10.5900","2. high":"10.6800","3. low":"10.4800","4. close":"10.6200","5. volume":"112830"},"2021-02-09":{"1. open":"10.5500","2. high":"10.5700","3. low":"10.4900","4. close":"10.5400","5. volume":"53067"},"2021-02-08":{"1. open":"10.5700","2. high":"10.6780","3. low":"10.5100","4. close":"10.5500","5. volume":"12551"},"2021-02-05":{"1. open":"10.7400","2. high":"10.7500","3. low":"10.5000","4. close":"10.5500","5. volume":"157860"},"2021-02-04":{"1. open":"10.5200","2. high":"10.7400","3. low":"10.5200","4. close":"10.6042","5. volume":"232471"},"2021-02-03":{"1. open":"10.4592","2. high":"10.5100","3. low":"10.4500","4. close":"10.5000","5. volume":"248989"},"2021-02-02":{"1. open":"10.3700","2. high":"10.5500","3. low":"10.3600","4. close":"10.5000","5. volume":"110463"},"2021-02-01":{"1. open":"10.4800","2. high":"10.5350","3. low":"10.3600","4. close":"10.4100","5. volume":"72170"},"2021-01-29":{"1. open":"10.3500","2. high":"10.4500","3. low":"10.3000","4. close":"10.4000","5. volume":"61435"},"2021-01-28":{"1. open":"10.3800","2. high":"10.4800","3. low":"10.3000","4. close":"10.4000","5. volume":"218541"},"2021-01-27":{"1. open":"10.4200","2. high":"10.5000","3. low":"10.3000","4. close":"10.3500","5. volume":"331050"},"2021-01-26":{"1. open":"10.5900","2. high":"10.6100","3. low":"10.4500","4. close":"10.5000","5. volume":"95181"},"2021-01-25":{"1. open":"10.6000","2. high":"10.8600","3. low":"10.5200","4. close":"10.5500","5. volume":"350847"},"2021-01-22":{"1. open":"10.4200","2. high":"10.5700","3. low":"10.4100","4. close":"10.4200","5. volume":"8607753"}}}