{"Meta Data":{"1. Information":"Daily Prices (open, high, low, close) and Volumes","2. Symbol":"XM","3. Last Refreshed":"2021-02-16 16:00:01","4. Output Size":"Full size","5. Time Zone":"US/Eastern"},"Time Series (Daily)":{"2021-02-16":{"1. open":"46.2100","2. high":"46.3500","3. low":"44.1000","4. close":"45.2400","5. volume":"1428959"},"2021-02-12":{"1. open":"46.0000","2. high":"46.9500","3. low":"45.0800","4. close":"45.3600","5. volume":"1368856"},"2021-02-11":{"1. open":"47.3000","2. high":"47.9500","3. low":"44.9600","4. close":"46.1100","5. volume":"1750709"},"2021-02-10":{"1. open":"49.4200","2. high":"49.8900","3. low":"45.5800","4. close":"46.0000","5. volume":"1960490"},"2021-02-09":{"1. open":"50.5100","2. high":"51.8499","3. low":"46.6000","4. close":"48.2900","5. volume":"2625802"},"2021-02-08":{"1. open":"54.7300","2. high":"54.9800","3. low":"50.4700","4. close":"50.5000","5. volume":"2217355"},"2021-02-05":{"1. open":"56.0000","2. high":"56.9800","3. low":"54.5100","4. close":"55.2400","5. volume":"5073394"},"2021-02-04":{"1. open":"54.9900","2. high":"57.2779","3. low":"53.6100","4. close":"54.9000","5. volume":"1925337"},"2021-02-03":{"1. open":"52.2000","2. high":"53.8000","3. low":"51.0400","4. close":"53.5000","5. volume":"6590467"},"2021-02-02":{"1. open":"49.7600","2. high":"54.1000","3. low":"49.4500","4. close":"51.2500","5. volume":"2916574"},"2021-02-01":{"1. open":"44.1400","2. high":"49.9000","3. low":"43.9500","4. close":"49.0000","5. volume":"4051069"},"2021-01-29":{"1. open":"47.0000","2. high":"48.3100","3. low":"41.8800","4. close":"44.0000","5. volume":"8514859"},"2021-01-28":{"1. open":"41.8500","2. high":"45.9600","3. low":"41.0800","4. close":"45.5000","5. volume":"25468626"}}}